<annotation>
  <folder>pic3</folder>
  <filename>00586</filename>
  <path>D:\16-17-3\yolo\pic3\00586.jpg</path>
  <source>
    <database>Unknown</database>
  </source>
  <size>
    <width>480</width>
    <height>270</height>
    <depth>3</depth>
  </size>
  <segmented>0</segmented>
  <object>
    <name>chariot</name>
    <pose>Unspecified</pose>
    <truncated>0</truncated>
    <difficult>0</difficult>
    <bndbox>
      <xmin>93</xmin>
      <ymin>62</ymin>
      <xmax>263</xmax>
      <ymax>253</ymax>
    </bndbox>
  </object>
  <object>
    <name>chariot</name>
    <pose>Unspecified</pose>
    <truncated>0</truncated>
    <difficult>0</difficult>
    <bndbox>
      <xmin>152</xmin>
      <ymin>64</ymin>
      <xmax>198</xmax>
      <ymax>110</ymax>
    </bndbox>
  </object>
  <object>
    <name>bag</name>
    <pose>Unspecified</pose>
    <truncated>0</truncated>
    <difficult>0</difficult>
    <bndbox>
      <xmin>11</xmin>
      <ymin>60</ymin>
      <xmax>71</xmax>
      <ymax>117</ymax>
    </bndbox>
  </object>
</annotation>
