<annotation>
  <folder>pic6</folder>
  <filename>01987</filename>
  <path>D:\professional\srtp\mysrtp\100MEDIA\pic\pic6\01987.jpg</path>
  <source>
    <database>Unknown</database>
  </source>
  <size>
    <width>480</width>
    <height>270</height>
    <depth>3</depth>
  </size>
  <segmented>0</segmented>
  <object>
    <name>bag</name>
    <pose>Unspecified</pose>
    <truncated>0</truncated>
    <difficult>0</difficult>
    <bndbox>
      <xmin>182</xmin>
      <ymin>79</ymin>
      <xmax>220</xmax>
      <ymax>154</ymax>
    </bndbox>
  </object>
  <object>
    <name>chariot</name>
    <pose>Unspecified</pose>
    <truncated>0</truncated>
    <difficult>0</difficult>
    <bndbox>
      <xmin>239</xmin>
      <ymin>82</ymin>
      <xmax>305</xmax>
      <ymax>165</ymax>
    </bndbox>
  </object>
  <object>
    <name>chariot</name>
    <pose>Unspecified</pose>
    <truncated>0</truncated>
    <difficult>0</difficult>
    <bndbox>
      <xmin>334</xmin>
      <ymin>75</ymin>
      <xmax>396</xmax>
      <ymax>158</ymax>
    </bndbox>
  </object>
  <object>
    <name>bag</name>
    <pose>Unspecified</pose>
    <truncated>0</truncated>
    <difficult>0</difficult>
    <bndbox>
      <xmin>333</xmin>
      <ymin>168</ymin>
      <xmax>435</xmax>
      <ymax>239</ymax>
    </bndbox>
  </object>
</annotation>
