<annotation>
  <folder>pic6</folder>
  <filename>02169</filename>
  <path>D:\professional\srtp\mysrtp\100MEDIA\pic\pic6\02169.jpg</path>
  <source>
    <database>Unknown</database>
  </source>
  <size>
    <width>480</width>
    <height>270</height>
    <depth>3</depth>
  </size>
  <segmented>0</segmented>
  <object>
    <name>chariot</name>
    <pose>Unspecified</pose>
    <truncated>0</truncated>
    <difficult>0</difficult>
    <bndbox>
      <xmin>72</xmin>
      <ymin>175</ymin>
      <xmax>208</xmax>
      <ymax>269</ymax>
    </bndbox>
  </object>
  <object>
    <name>chariot</name>
    <pose>Unspecified</pose>
    <truncated>0</truncated>
    <difficult>0</difficult>
    <bndbox>
      <xmin>234</xmin>
      <ymin>132</ymin>
      <xmax>335</xmax>
      <ymax>268</ymax>
    </bndbox>
  </object>
  <object>
    <name>bag</name>
    <pose>Unspecified</pose>
    <truncated>0</truncated>
    <difficult>0</difficult>
    <bndbox>
      <xmin>1</xmin>
      <ymin>159</ymin>
      <xmax>79</xmax>
      <ymax>263</ymax>
    </bndbox>
  </object>
  <object>
    <name>box</name>
    <pose>Unspecified</pose>
    <truncated>0</truncated>
    <difficult>0</difficult>
    <bndbox>
      <xmin>241</xmin>
      <ymin>79</ymin>
      <xmax>325</xmax>
      <ymax>163</ymax>
    </bndbox>
  </object>
</annotation>
