<annotation>
  <folder>pic2</folder>
  <filename>02973</filename>
  <path>D:\Documents\Tencent Files\767422171\FileRecv\outputpic2\pic2\02973.jpg</path>
  <source>
    <database>Unknown</database>
  </source>
  <size>
    <width>480</width>
    <height>270</height>
    <depth>3</depth>
  </size>
  <segmented>0</segmented>
  <object>
    <name>chariot</name>
    <pose>Unspecified</pose>
    <truncated>0</truncated>
    <difficult>0</difficult>
    <bndbox>
      <xmin>271</xmin>
      <ymin>9</ymin>
      <xmax>342</xmax>
      <ymax>114</ymax>
    </bndbox>
  </object>
</annotation>
